COPYING
MANIFEST.in
README.rst
bootstrap.py
buildout.cfg
setup.py
docs/conf.py
docs/index.rst
xbob/__init__.py
xbob.db.xm2vts.egg-info/PKG-INFO
xbob.db.xm2vts.egg-info/SOURCES.txt
xbob.db.xm2vts.egg-info/dependency_links.txt
xbob.db.xm2vts.egg-info/entry_points.txt
xbob.db.xm2vts.egg-info/namespace_packages.txt
xbob.db.xm2vts.egg-info/not-zip-safe
xbob.db.xm2vts.egg-info/requires.txt
xbob.db.xm2vts.egg-info/top_level.txt
xbob/db/__init__.py
xbob/db/xm2vts/__init__.py
xbob/db/xm2vts/create.py
xbob/db/xm2vts/db.sql3
xbob/db/xm2vts/driver.py
xbob/db/xm2vts/models.py
xbob/db/xm2vts/query.py
xbob/db/xm2vts/test.py