Metadata-Version: 1.1
Name: xbob.db.xm2vts
Version: 1.2.0
Summary: XM2VTS Database Access API for Bob
Home-page: https://pypi.python.org/pypi/xbob.db.xm2vts
Author: Laurent El Shafey
Author-email: laurent.el-shafey@idiap.ch
License: GPLv3
Keywords: face recognition,bob,xbob,xbob.db,XM2VTS
Platform: UNKNOWN
Classifier: Development Status :: 5 - Production/Stable
Classifier: Environment :: Console
Classifier: Intended Audience :: Developers
Classifier: Intended Audience :: Education
Classifier: Intended Audience :: Science/Research
Classifier: License :: OSI Approved :: GNU General Public License v3 (GPLv3)
Classifier: Natural Language :: English
Classifier: Programming Language :: Python
Classifier: Programming Language :: Python :: 3
Classifier: Topic :: Scientific/Engineering :: Artificial Intelligence
Classifier: Topic :: Database :: Front-Ends
